{
  "id": "frontend-api-mock-isolation",
  "name": "frontend-api-mock-isolation",
  "title": "Frontend API mock isolation",
  "description": "Start the frontend API/mock architecture split by migrating the demand domain to features/demand/api.ts, moving demand mock storage under src/mocks, and enforcing real-only production mock guards.",
  "status": "in_progress",
  "dev_type": null,
  "scope": "frontend",
  "package": "frontend",
  "priority": "P0",
  "creator": "xiangrikuil",
  "assignee": "xiangrikuil",
  "createdAt": "2026-07-06",
  "completedAt": null,
  "branch": null,
  "base_branch": "main",
  "worktree_path": null,
  "commit": null,
  "pr_url": null,
  "subtasks": [],
  "children": [],
  "parent": "07-06-maintenance-hardening-roadmap",
  "relatedFiles": [],
  "notes": "",
  "meta": {}
}